alveolus/.DS_Store
alveolus/__init__.py
alveolus/alveolus-config.ini
alveolus/conf.py
alveolus/dependency_check.py
alveolus/hooks.py
alveolus/main.py
alveolus/settings.py
alveolus/tools/Makefile.in
alveolus/tools/create-docs.sh
alveolus/tools/doxygen.conf.in
alveolus/tools/index.rst.in
alveolus/tools/make.bat.in
exhale/.DS_Store
exhale/__init__.py
exhale/configs.py
exhale/deploy.py
exhale/graph.py
exhale/parse.py
exhale/utils.py
exhale/data/treeView/collapsible-lists/LICENSE.md
exhale/data/treeView/collapsible-lists/css/button-closed.png
exhale/data/treeView/collapsible-lists/css/button-open.png
exhale/data/treeView/collapsible-lists/css/button.png
exhale/data/treeView/collapsible-lists/css/list-item-contents.png
exhale/data/treeView/collapsible-lists/css/list-item-last-open.png
exhale/data/treeView/collapsible-lists/css/list-item-last.png
exhale/data/treeView/collapsible-lists/css/list-item-open.png
exhale/data/treeView/collapsible-lists/css/list-item-root.png
exhale/data/treeView/collapsible-lists/css/list-item.png
exhale/data/treeView/collapsible-lists/css/tree_view.css
exhale/data/treeView/collapsible-lists/js/CollapsibleLists.compressed.js
exhale/data/treeView/collapsible-lists/js/apply-collapsible-lists.js
exhale/data/treeView-bootstrap/bootstrap-treeview/LICENSE
exhale/data/treeView-bootstrap/bootstrap-treeview/apply-bootstrap-treview.js
exhale/data/treeView-bootstrap/bootstrap-treeview/bootstrap-treeview.min.css
exhale/data/treeView-bootstrap/bootstrap-treeview/bootstrap-treeview.min.js
alveolus-0.1.2.dist-info/LICENSE
alveolus-0.1.2.dist-info/METADATA
alveolus-0.1.2.dist-info/WHEEL
alveolus-0.1.2.dist-info/entry_points.txt
alveolus-0.1.2.dist-info/top_level.txt
alveolus-0.1.2.dist-info/RECORD
