Metadata-Version: 2.1
Name: alveolus
Version: 0.1.2
Summary: Alveolus Docs,provides a very simple way, to create read the docs alike documentation for c++ projects.With the help of breathe and exhale it combines Doxygen and sphinx to enable tou to createcode documentation as well as custom documentation files
Home-page: https://github.com/johnkozaris/alveolus
Author: Ioannis Kozaris
Author-email: ioanniskozaris@gmail.com
License: MIT
Keywords: documentation sphinx doxygen C++ docs
Platform: UNKNOWN
Classifier: Programming Language :: Python :: 3
Classifier: Programming Language :: Python :: 3.3
Classifier: Framework :: Sphinx
Classifier: Intended Audience :: Developers
Classifier: Environment :: Console
Classifier: License :: OSI Approved :: BSD License
Classifier: Programming Language :: C++
Classifier: Operating System :: OS Independent
Classifier: Topic :: Documentation
Classifier: Topic :: Documentation :: Sphinx
Classifier: Topic :: Software Development :: Documentation
Requires-Python: ~=3.3
Requires-Dist: sphinx
Requires-Dist: breathe
